fnschoo1/__init__.py
fnschoo1/manage.py
fnschoo1/canteen/__init__.py
fnschoo1/canteen/admin.py
fnschoo1/canteen/apps.py
fnschoo1/canteen/forms.py
fnschoo1/canteen/models.py
fnschoo1/canteen/tests.py
fnschoo1/canteen/urls.py
fnschoo1/canteen/views.py
fnschoo1/canteen/migrations/0001_initial.py
fnschoo1/canteen/migrations/0002_ingredient_is_disabled.py
fnschoo1/canteen/migrations/0003_consumption_is_disabled_alter_ingredient_is_disabled.py
fnschoo1/canteen/migrations/0004_alter_ingredient_name_category_and_more.py
fnschoo1/canteen/migrations/0005_alter_category_created_at_alter_category_name_and_more.py
fnschoo1/canteen/migrations/0006_category_is_disabled_alter_category_user_and_more.py
fnschoo1/canteen/migrations/0007_alter_consumption_amount_used_and_more.py
fnschoo1/canteen/migrations/0008_category_abbreviation_mealtype.py
fnschoo1/canteen/migrations/0009_alter_category_abbreviation_and_more.py
fnschoo1/canteen/migrations/0010_alter_consumption_options_alter_ingredient_options_and_more.py
fnschoo1/canteen/migrations/0011_category_pin_to_consumptions_top.py
fnschoo1/canteen/migrations/0012_alter_ingredient_storage_date.py
fnschoo1/canteen/migrations/0013_alter_consumption_options_alter_ingredient_options_and_more.py
fnschoo1/canteen/migrations/0014_category_priority.py
fnschoo1/canteen/migrations/0015_alter_category_options_alter_category_priority.py
fnschoo1/canteen/migrations/0016_consumption_unique_ingredient_date_of_using.py
fnschoo1/canteen/migrations/0017_ingredient_updated_at_alter_category_created_at_and_more.py
fnschoo1/canteen/migrations/0018_alter_ingredient_updated_at.py
fnschoo1/canteen/migrations/0019_category_updated_at_ingredient_created_at_and_more.py
fnschoo1/canteen/migrations/0020_alter_ingredient_created_at.py
fnschoo1/canteen/migrations/0021_alter_category_updated_at_and_more.py
fnschoo1/canteen/migrations/0022_alter_category_updated_at_and_more.py
fnschoo1/canteen/migrations/0023_alter_consumption_options_alter_ingredient_options_and_more.py
fnschool-20260106.81609.859.dist-info/licenses/LICENSE
fnschool-20260106.81609.859.dist-info/METADATA
fnschool-20260106.81609.859.dist-info/WHEEL
fnschool-20260106.81609.859.dist-info/entry_points.txt
fnschool-20260106.81609.859.dist-info/top_level.txt
fnschool-20260106.81609.859.dist-info/RECORD
