Metadata-Version: 2.4
Name: fnschool
Version: 20260106.81609.859
Summary: Just some school related scripts, without any ambition.
Author-email: larryw3i <larryw3i@163.com>, Larry Wei <larryw3i@126.com>, Larry W3i <larryw3i@yeah.net>
Maintainer-email: larryw3i <larryw3i@163.com>, Larry Wei <larryw3i@126.com>
Project-URL: Homepage, https://github.com/larryw3i/funingschool
Project-URL: Documentation, https://github.com/larryw3i/funingschool/docs
Project-URL: Repository, https://github.com/larryw3i/funingschool.git
Project-URL: Issues, https://github.com/larryw3i/funingschool/issues
Project-URL: Changelog, https://github.com/larryw3i/funingschool/CHANGELOG.md
Classifier: Topic :: Education
Classifier: Programming Language :: Python :: 3.10
Requires-Python: >=3.9
License-File: LICENSE
Requires-Dist: django
Requires-Dist: pandas
Requires-Dist: matplotlib
Requires-Dist: numpy
Requires-Dist: openpyxl
Requires-Dist: platformdirs
Requires-Dist: tomlkit
Requires-Dist: django-crispy-forms
Requires-Dist: crispy-bootstrap5
Provides-Extra: gui
Provides-Extra: cli
Dynamic: license-file
